[
  {
    "id": 1,
    "email": "john@mail.com",
    "name": "Jhon"
  },
  {
    "id": 2,
    "email": "maria@mail.com",
    "name": "Maria"
  },
  {
    "id": 3,
    "email": "admin@mail.com",
    "name": "Admin"
  },
  {
    "id": 4,
    "email": "beko@gmail.com",
    "name": "beko"
  },
  {
    "id": 6,
    "email": "nico@gmail.com",
    "name": "Nicolas"
  },
  {
    "id": 7,
    "email": "nico@gmail.com",
    "name": "Nicolas"
  },
  {
    "id": 8,
    "email": "nico@gmail.com",
    "name": "Nicolas"
  },
  {
    "id": 9,
    "email": "nico@gmail.com",
    "name": "Nicolas"
  },
  {
    "id": 10,
    "email": "nico@gmail.com",
    "name": "Nicolas"
  },
  {
    "id": 11,
    "email": "nico@gmail.com",
    "name": "Nicolas"
  },
  {
    "id": 12,
    "email": "nico@gmail.com",
    "name": "Nicolas"
  },
  {
    "id": 13,
    "email": "nico@gmail.com",
    "name": "Nicolas"
  },
  {
    "id": 14,
    "email": "nico@gmail.com",
    "name": "Nicolas"
  },
  {
    "id": 15,
    "email": "bido@mail.com",
    "name": "bido"
  },
  {
    "id": 27,
    "email": "hjvbjhvguyf@gmail.com",
    "name": "nora"
  },
  {
    "id": 28,
    "email": "hjvbjhvguyf@gmail.com",
    "name": "nora"
  },
  {
    "id": 29,
    "email": "hjvbjhvguyf@gmail.com",
    "name": "nora"
  },
  {
    "id": 30,
    "email": "hjvbjhvguyf@gmail.com",
    "name": "nora"
  },
  {
    "id": 31,
    "email": "hjvbjhvguyf@gmail.com",
    "name": "nora"
  },
  {
    "id": 32,
    "email": "hjvbjhvguyf@gmail.com",
    "name": "nora"
  },
  {
    "id": 33,
    "email": "hjvbjhvguyf@gmail.com",
    "name": "nora"
  },
  {
    "id": 34,
    "email": "hjvbjhvguyf@gmail.com",
    "name": "nora"
  },
  {
    "id": 35,
    "email": "hjvbjhvguyf@gmail.com",
    "name": "nora"
  },
  {
    "id": 36,
    "email": "hjvbjhvguyf@gmail.com",
    "name": "nora"
  },
  {
    "id": 37,
    "email": "hacker1777072795@test.com",
    "name": "Hacker"
  },
  {
    "id": 38,
    "email": "hjvbjhvguyf@gmail.com",
    "name": "nora"
  },
  {
    "id": 39,
    "email": "hjvbjhvguyf@gmail.com",
    "name": "nora"
  },
  {
    "id": 40,
    "email": "hjvbjhvguyf@gmail.com",
    "name": "nora"
  },
  {
    "id": 41,
    "email": "john@mail.com",
    "name": "Duplicate"
  },
  {
    "id": 42,
    "email": "ugfiuf@gmail.com",
    "name": "Nora"
  },
  {
    "id": 43,
    "email": "admintest1777073096@test.com",
    "name": "AdminTest1777073096"
  },
  {
    "id": 44,
    "email": "race1777073148@test.com",
    "name": "Race User"
  },
  {
    "id": 45,
    "email": "race1777073148@test.com",
    "name": "Race User"
  },
  {
    "id": 46,
    "email": "race1777073148@test.com",
    "name": "Race User"
  },
  {
    "id": 47,
    "email": "race1777073148@test.com",
    "name": "Race User"
  },
  {
    "id": 48,
    "email": "race1777073148@test.com",
    "name": "Race User"
  },
  {
    "id": 49,
    "email": "race1777073148@test.com",
    "name": "Race User"
  },
  {
    "id": 50,
    "email": "race1777073148@test.com",
    "name": "Race User"
  },
  {
    "id": 51,
    "email": "race1777073148@test.com",
    "name": "Race User"
  },
  {
    "id": 52,
    "email": "race1777073148@test.com",
    "name": "Race User"
  },
  {
    "id": 53,
    "email": "race1777073148@test.com",
    "name": "Race User"
  }
]